powrap/__init__.py
powrap/__main__.py
powrap/powrap.py
powrap-1.0.2.dist-info/LICENSE
powrap-1.0.2.dist-info/METADATA
powrap-1.0.2.dist-info/WHEEL
powrap-1.0.2.dist-info/entry_points.txt
powrap-1.0.2.dist-info/top_level.txt
powrap-1.0.2.dist-info/RECORD
