Metadata-Version: 2.1
Name: powrap
Version: 1.0.2
Summary: Find and properly reindent .po files.
Author-email: Julien Palard <julien@palard.fr>
License: MIT License
Project-URL: Homepage, https://git.afpy.org/AFPy/powrap
Keywords: powrap,po,gettext,i18n
Classifier: Development Status :: 5 - Production/Stable
Classifier: Intended Audience :: Developers
Classifier: License :: OSI Approved :: MIT License
Classifier: Natural Language :: English
Classifier: Programming Language :: Python :: 3
Requires-Python: >=3.7
License-File: LICENSE
Requires-Dist: tqdm
